krakentren/__init__.py
krakentren/krakentren.py
krakentren/ta.py
krakentren-0.11.19.dist-info/LICENSE.txt
krakentren-0.11.19.dist-info/METADATA
krakentren-0.11.19.dist-info/WHEEL
krakentren-0.11.19.dist-info/top_level.txt
krakentren-0.11.19.dist-info/RECORD
